multisigwallet_predeployed/__init__.py
multisigwallet_predeployed/address.py
multisigwallet_predeployed/multisigwallet_generator.py
multisigwallet_predeployed/py.typed
multisigwallet_predeployed/artifacts/.keep
multisigwallet_predeployed/artifacts/MultiSigWallet.json
multisigwallet_predeployed/artifacts/MultiSigWallet.meta.json
multisigwallet_predeployed-1.1.0a9.dist-info/METADATA
multisigwallet_predeployed-1.1.0a9.dist-info/WHEEL
multisigwallet_predeployed-1.1.0a9.dist-info/top_level.txt
multisigwallet_predeployed-1.1.0a9.dist-info/RECORD
