Metadata-Version: 2.1
Name: multisigwallet-predeployed
Version: 1.1.0a9
Summary: A tool for generating predeployed MultiSigWallet smart contract
Home-page: https://github.com/skalenetwork/multisigwallet-predeployed
Author: Vadim Yavorsky
Author-email: vadim@skalelabs.com
Classifier: Programming Language :: Python :: 3
Classifier: License :: OSI Approved :: GNU Affero General Public License v3
Classifier: Operating System :: OS Independent
Requires-Python: >=3.7
Requires-Dist: predeployed-generator>=1.1.0a1
